setup.py
ain/__init__.py
ain/ain.py
ain/constants.py
ain/instanceUtil.py
ain/workerMgr.py
ain/share/worker.env
ain/share/log/log.env
ainainain.egg-info/PKG-INFO
ainainain.egg-info/SOURCES.txt
ainainain.egg-info/dependency_links.txt
ainainain.egg-info/entry_points.txt
ainainain.egg-info/requires.txt
ainainain.egg-info/top_level.txt