Metadata-Version: 1.2
Name: ainainain
Version: 1.0
Summary: CLI of ainainain a Python script
Home-page: https://bitbucket.org/comcomai/ain-worker
License: BSD
Platform: UNKNOWN
Classifier: License :: OSI Approved :: BSD License
Requires-Python: >=3.6
